setup.py
setz.py
setz_funcs.py
Setz.egg-info/PKG-INFO
Setz.egg-info/SOURCES.txt
Setz.egg-info/dependency_links.txt
Setz.egg-info/top_level.txt
bin/setz