Metadata-Version: 1.0
Name: Setz
Version: 0.0.1
Summary: Queries set operators from files using python syntax
Home-page: https://github.com/Doboy/Setz
Author: Huan Do
Author-email: doboy0@gmail.com
License: UNKNOWN
Platform: UNKNOWN
